pdan/__init__.py
pdan/pdan.py
pdan-0.1.9.dist-info/LICENSE
pdan-0.1.9.dist-info/METADATA
pdan-0.1.9.dist-info/WHEEL
pdan-0.1.9.dist-info/RECORD
