Metadata-Version: 2.1
Name: pdan
Version: 0.1.9
Summary: 
Author: GeorgySk
Author-email: skorobogatov@phystech.edu
Requires-Python: >=3.8,<4.0
Classifier: Programming Language :: Python :: 3
Classifier: Programming Language :: Python :: 3.8
Classifier: Programming Language :: Python :: 3.9
Classifier: Programming Language :: Python :: 3.10
Classifier: Programming Language :: Python :: 3.11
Classifier: Programming Language :: Python :: 3.12
Requires-Dist: gon (>=5.0.0,<6.0.0)
